dh/cli.py
dh/context.py
dh/commands/__init__.py
dh/commands/auth.py
dh/commands/build.py
dh/commands/clean.py
dh/commands/db.py
dh/commands/dev.py
dh/commands/make.py
dh/commands/setup.py
dh/commands/validate.py
dh/utils/__init__.py
dh/utils/commands.py
dh/utils/config.py
dh/utils/db.py
dh/utils/detection.py
dh/utils/env.py
dh/utils/prompts.py
devhand-0.4.13.dist-info/METADATA
devhand-0.4.13.dist-info/WHEEL
devhand-0.4.13.dist-info/entry_points.txt
devhand-0.4.13.dist-info/licenses/LICENSE
devhand-0.4.13.dist-info/RECORD
