Metadata-Version: 2.4
Name: devhand
Version: 0.4.13
Summary: CLI tool to improve devX for webapps
Project-URL: Homepage, https://github.com/dskarbrevik/devhand
Project-URL: Issues, https://github.com/dskarbrevik/devhand/issues
License-File: LICENSE
Requires-Python: >=3.11
Requires-Dist: requests>=2.32.0
Requires-Dist: rich>=14.2.0
Requires-Dist: supabase>=2.27.0
Requires-Dist: typer>=0.21.0
